ShujuwajueShidaSuanfaXiangjie/README.md
ShujuwajueShidaSuanfaXiangjie/__init__.py
ShujuwajueShidaSuanfaXiangjie/__main__.py
ShujuwajueShidaSuanfaXiangjie/file.epub
ShujuwajueShidaSuanfaXiangjie/index.html
ShujuwajueShidaSuanfaXiangjie/css/__init__.py
ShujuwajueShidaSuanfaXiangjie/css/annotations.css
ShujuwajueShidaSuanfaXiangjie/css/main.css
ShujuwajueShidaSuanfaXiangjie/css/normalize.css
ShujuwajueShidaSuanfaXiangjie/css/popup.css
ShujuwajueShidaSuanfaXiangjie/font/__init__.py
ShujuwajueShidaSuanfaXiangjie/font/fontello.eot
ShujuwajueShidaSuanfaXiangjie/font/fontello.svg
ShujuwajueShidaSuanfaXiangjie/font/fontello.ttf
ShujuwajueShidaSuanfaXiangjie/font/fontello.woff
ShujuwajueShidaSuanfaXiangjie/img/__init__.py
ShujuwajueShidaSuanfaXiangjie/img/annotator-glyph-sprite.png
ShujuwajueShidaSuanfaXiangjie/img/annotator-icon-sprite.png
ShujuwajueShidaSuanfaXiangjie/img/apple-touch-icon.png
ShujuwajueShidaSuanfaXiangjie/img/cancelfullscreen.png
ShujuwajueShidaSuanfaXiangjie/img/close.png
ShujuwajueShidaSuanfaXiangjie/img/fullscreen.png
ShujuwajueShidaSuanfaXiangjie/img/loader.gif
ShujuwajueShidaSuanfaXiangjie/img/menu-icon.png
ShujuwajueShidaSuanfaXiangjie/img/save.png
ShujuwajueShidaSuanfaXiangjie/img/saved.png
ShujuwajueShidaSuanfaXiangjie/img/settings-s.png
ShujuwajueShidaSuanfaXiangjie/img/settings.png
ShujuwajueShidaSuanfaXiangjie/img/star.png
ShujuwajueShidaSuanfaXiangjie/js/__init__.py
ShujuwajueShidaSuanfaXiangjie/js/epub.js
ShujuwajueShidaSuanfaXiangjie/js/epub.min.js
ShujuwajueShidaSuanfaXiangjie/js/epub.min.map
ShujuwajueShidaSuanfaXiangjie/js/hooks.min.js
ShujuwajueShidaSuanfaXiangjie/js/hooks.min.map
ShujuwajueShidaSuanfaXiangjie/js/reader.js
ShujuwajueShidaSuanfaXiangjie/js/reader.js.map
ShujuwajueShidaSuanfaXiangjie/js/reader.min.js
ShujuwajueShidaSuanfaXiangjie/js/reader.min.map
ShujuwajueShidaSuanfaXiangjie/js/hooks/__init__.py
ShujuwajueShidaSuanfaXiangjie/js/hooks/extensions/__init__.py
ShujuwajueShidaSuanfaXiangjie/js/hooks/extensions/highlight.js
shujuwajue_shida_suanfa_xiangjie-2024.3.2.0.dist-info/METADATA
shujuwajue_shida_suanfa_xiangjie-2024.3.2.0.dist-info/WHEEL
shujuwajue_shida_suanfa_xiangjie-2024.3.2.0.dist-info/entry_points.txt
shujuwajue_shida_suanfa_xiangjie-2024.3.2.0.dist-info/top_level.txt
shujuwajue_shida_suanfa_xiangjie-2024.3.2.0.dist-info/RECORD
